nwos/__init__.py
nwos/nwos.py
nwos-0.3.dist-info/LICENSE
nwos-0.3.dist-info/METADATA
nwos-0.3.dist-info/WHEEL
nwos-0.3.dist-info/top_level.txt
nwos-0.3.dist-info/RECORD
