Metadata-Version: 2.1
Name: nwos
Version: 0.3
Summary: A library for working with prime and composite numbers
Home-page: https://github.com/yourusername/nwos
Author: Nlolik1111
Author-email: nikolay9047670014@gmail.com
Classifier: Programming Language :: Python :: 3
Classifier: License :: OSI Approved :: MIT License
Classifier: Operating System :: OS Independent
Requires-Python: >=3.6
License-File: LICENSE
